setup.py
timedprocess.py
timedprocess.py.egg-info/PKG-INFO
timedprocess.py.egg-info/SOURCES.txt
timedprocess.py.egg-info/dependency_links.txt
timedprocess.py.egg-info/entry_points.txt
timedprocess.py.egg-info/requires.txt
timedprocess.py.egg-info/top_level.txt