Metadata-Version: 1.0
Name: timedprocess.py
Version: 1.0a2
Summary: Run a program for a specified duration
Home-page: https://github.com/koldof/timedprocess.py
Author: koldof
Author-email: king.koldof@gmail.com
License: GPLv3
Keywords: timed processes
Platform: UNKNOWN
